src/__init__.py
src/main.py
KataRangePair-0.0.1.dist-info/LICENSE
KataRangePair-0.0.1.dist-info/METADATA
KataRangePair-0.0.1.dist-info/WHEEL
KataRangePair-0.0.1.dist-info/top_level.txt
KataRangePair-0.0.1.dist-info/RECORD
