Metadata-Version: 2.1
Name: KataRangePair
Version: 0.0.1
Summary: <App about Coding dojo - Kata Range>
Home-page: UNKNOWN
Author: <Leonel Rodriguez - Carlos Rosario
Author-email: <leonelr0307@gmail.com>
License: UNKNOWN
Platform: UNKNOWN
Classifier: Programming Language :: Python :: 3
Classifier: License :: OSI Approved :: MIT License
Classifier: Operating System :: OS Independent
License-File: LICENSE
